{
  "topBar": {
    "links": [
      { "label": "Đăng nhập", "href": "#" },
      { "label": "Đăng ký tài khoản", "href": "#" },
      { "label": "Nạp tài khoản", "href": "#" },
      { "label": "Danh sách dịch vụ", "href": "#", "hasDropdown": true },
      { "label": "Danh sách game", "href": "#", "hasDropdown": true, "highlight": true }
    ]
  },
  "header": {
    "navItems": [
      { "label": "Trang chủ", "href": "/", "isExternal": false },
      { "label": "Nhóm zalo", "href": "#", "isExternal": false },
      { "label": "Page FB", "href": "#", "isExternal": false }
    ]
  },
  "footer": {
    "supportLinks": [
      { "label": "Về chúng tôi", "href": "#" },
      { "label": "Điều khoản dịch vụ", "href": "#" },
      { "label": "Trung tâm hỗ trợ", "href": "#" },
      { "label": "Liên hệ", "href": "#" },
      { "label": "Tuyển dụng", "href": "#" }
    ]
  }
}
